tsvkit/__init__.py
tsvkit-0.5.5.dist-info/METADATA
tsvkit-0.5.5.dist-info/WHEEL
tsvkit-0.5.5.dist-info/entry_points.txt
tsvkit-0.5.5.dist-info/top_level.txt
tsvkit-0.5.5.dist-info/RECORD
