Metadata-Version: 2.1
Name: tsvkit
Version: 0.5.5
Summary: TSV toolkit
Home-page: https://github.com/5xc/tsvkit/
Author: singchen
Author-email: xhqsm@qq.com
License: MIT
Platform: UNKNOWN
Requires-Dist: openpyxl
Requires-Dist: xlrd
